__init__.py
cachesaver/__init__.py
cachesaver/batching.py
cachesaver/caching.py
cachesaver/deduplicator.py
cachesaver/model.py
cachesaver/pipelines.py
cachesaver/reordering.py
cachesaver/resources.py
cachesaver/typedefs.py
cachesaver/models/__init__.py
cachesaver/models/openai.py
cachesaver/models/together.py
cachesaver/models/wrapper.py
cachesaver/resource_managers/__init__.py
cachesaver/resource_managers/round_robin.py
cachesaver/resource_managers/unlimited.py
cachesaver-0.0.2.dist-info/licenses/LICENSE
cachesaver-0.0.2.dist-info/METADATA
cachesaver-0.0.2.dist-info/WHEEL
cachesaver-0.0.2.dist-info/top_level.txt
cachesaver-0.0.2.dist-info/RECORD
