Metadata-Version: 2.4
Name: cachesaver
Version: 0.0.2
Summary: A caching library built with LLM experiments in mind
Author-email: Lars Klein <lars.klein@epfl.ch>
Classifier: Programming Language :: Python :: 3
Classifier: Operating System :: OS Independent
Requires-Python: >=3.10
License-File: LICENSE
Requires-Dist: deepdiff
Requires-Dist: diskcache
Requires-Dist: openai
Requires-Dist: together
Provides-Extra: test
Requires-Dist: pytest>=7.0.0; extra == "test"
Requires-Dist: pytest-asyncio>=0.21.0; extra == "test"
Requires-Dist: pytest-cov>=4.1.0; extra == "test"
Requires-Dist: deepdiff; extra == "test"
Requires-Dist: diskcache; extra == "test"
Dynamic: license-file
